Metadata-Version: 1.0
Name: beot-ggot
Version: 0.1
Summary: new package
Home-page: UNKNOWN
Author: UNKNOWN
Author-email: UNKNOWN
License: UNKNOWN
Platform: UNKNOWN
